playvideo/__init__.py
playvideo/_async_client.py
playvideo/_client.py
playvideo/errors.py
playvideo/types.py
playvideo/webhook.py
playvideo/_internal/__init__.py
playvideo/_internal/http.py
playvideo/resources/__init__.py
playvideo/resources/account.py
playvideo/resources/api_keys.py
playvideo/resources/collections.py
playvideo/resources/embed.py
playvideo/resources/usage.py
playvideo/resources/videos.py
playvideo/resources/webhooks.py
playvideo_python-1.0.0.dist-info/METADATA
playvideo_python-1.0.0.dist-info/WHEEL
playvideo_python-1.0.0.dist-info/licenses/LICENSE
playvideo_python-1.0.0.dist-info/RECORD
