Metadata-Version: 2.4
Name: playvideo-python
Version: 1.0.0
Summary: Official PlayVideo SDK for Python - Video hosting for developers
Project-URL: Homepage, https://playvideo.dev
Project-URL: Documentation, https://playvideo.dev/docs
Project-URL: Repository, https://github.com/PlayVideo-dev/playvideo-python
Project-URL: Issues, https://github.com/PlayVideo-dev/playvideo-python/issues
Author-email: PlayVideo <support@playvideo.dev>
License: MIT
License-File: LICENSE
Keywords: api,hls,playvideo,sdk,streaming,transcoding,video,video-hosting
Classifier: Development Status :: 5 - Production/Stable
Classifier: Intended Audience :: Developers
Classifier: License :: OSI Approved :: MIT License
Classifier: Operating System :: OS Independent
Classifier: Programming Language :: Python :: 3
Classifier: Programming Language :: Python :: 3.10
Classifier: Programming Language :: Python :: 3.11
Classifier: Programming Language :: Python :: 3.12
Classifier: Programming Language :: Python :: 3.13
Classifier: Topic :: Multimedia :: Video
Classifier: Topic :: Software Development :: Libraries :: Python Modules
Classifier: Typing :: Typed
Requires-Python: >=3.10
Requires-Dist: httpx>=0.25.0
Provides-Extra: dev
Requires-Dist: mypy>=1.0.0; extra == 'dev'
Requires-Dist: pytest-asyncio>=0.21.0; extra == 'dev'
Requires-Dist: pytest-httpx>=0.22.0; extra == 'dev'
Requires-Dist: pytest>=7.0.0; extra == 'dev'
Requires-Dist: ruff>=0.1.0; extra == 'dev'
